zope.formlib-6.0-py3.9-nspkg.pth
zope/formlib/TODO.rst
zope/formlib/__init__.py
zope/formlib/_compat.py
zope/formlib/boolwidgets.py
zope/formlib/bugs.rst
zope/formlib/configure.zcml
zope/formlib/errors.py
zope/formlib/errors.rst
zope/formlib/exception.py
zope/formlib/form.py
zope/formlib/form.rst
zope/formlib/ftesting.zcml
zope/formlib/i18n.py
zope/formlib/interfaces.py
zope/formlib/itemswidgets.py
zope/formlib/namedtemplate.py
zope/formlib/objectwidget.pt
zope/formlib/objectwidget.py
zope/formlib/objectwidget.rst
zope/formlib/orderedSelectionList.pt
zope/formlib/pageform.pt
zope/formlib/sequencewidget.pt
zope/formlib/sequencewidget.py
zope/formlib/source.py
zope/formlib/source.rst
zope/formlib/subpageform.pt
zope/formlib/textwidgets.py
zope/formlib/utility.py
zope/formlib/widget.py
zope/formlib/widget_macros.pt
zope/formlib/widgets.py
zope/formlib/widgets.rst
zope/formlib/js/ordered_selection.js
zope/formlib/js/pageform.js
zope/formlib/tests/__init__.py
zope/formlib/tests/functionalsupport.py
zope/formlib/tests/registerWidgets.zcml
zope/formlib/tests/support.py
zope/formlib/tests/test_browserwidget.py
zope/formlib/tests/test_checkboxwidget.py
zope/formlib/tests/test_choicecollections.py
zope/formlib/tests/test_choicewidget.py
zope/formlib/tests/test_datetimewidget.py
zope/formlib/tests/test_datewidget.py
zope/formlib/tests/test_decimalwidget.py
zope/formlib/tests/test_displaywidget.py
zope/formlib/tests/test_exception.py
zope/formlib/tests/test_filewidget.py
zope/formlib/tests/test_floatwidget.py
zope/formlib/tests/test_form.py
zope/formlib/tests/test_formlib.py
zope/formlib/tests/test_functional_booleanradiowidget.py
zope/formlib/tests/test_functional_checkboxwidget.py
zope/formlib/tests/test_functional_datetimewidget.py
zope/formlib/tests/test_functional_decimalwidget.py
zope/formlib/tests/test_functional_filewidget.py
zope/formlib/tests/test_functional_floatwidget.py
zope/formlib/tests/test_functional_intwidget.py
zope.formlib-6.0.dist-info/LICENSE.txt
zope.formlib-6.0.dist-info/METADATA
zope.formlib-6.0.dist-info/WHEEL
zope.formlib-6.0.dist-info/namespace_packages.txt
zope.formlib-6.0.dist-info/top_level.txt
zope.formlib-6.0.dist-info/RECORD
