Metadata-Version: 2.1
Name: zope.formlib
Version: 6.0
Summary: Form generation and validation library for Zope
Home-page: https://github.com/zopefoundation/zope.formlib
Author: Zope Foundation and Contributors
Author-email: zope-dev@zope.dev
License: ZPL 2.1
Keywords: zope3 form widget
Classifier: Development Status :: 5 - Production/Stable
Classifier: Environment :: Web Environment
Classifier: Intended Audience :: Developers
Classifier: License :: OSI Approved :: Zope Public License
Classifier: Programming Language :: Python
Classifier: Programming Language :: Python :: 3
Classifier: Programming Language :: Python :: 3.7
Classifier: Programming Language :: Python :: 3.8
Classifier: Programming Language :: Python :: 3.9
Classifier: Programming Language :: Python :: 3.10
Classifier: Programming Language :: Python :: 3.11
Classifier: Programming Language :: Python :: Implementation :: CPython
Classifier: Programming Language :: Python :: Implementation :: PyPy
Classifier: Natural Language :: English
Classifier: Operating System :: OS Independent
Classifier: Topic :: Internet :: WWW/HTTP
Classifier: Framework :: Zope :: 3
Requires-Python: >=3.7
License-File: LICENSE.txt
Requires-Dist: setuptools
Requires-Dist: pytz
Requires-Dist: zope.browser (>=1.1)
Requires-Dist: zope.browserpage (>=3.11.0)
Requires-Dist: zope.browserresource
Requires-Dist: zope.component
Requires-Dist: zope.event
Requires-Dist: zope.i18n
Requires-Dist: zope.i18nmessageid
Requires-Dist: zope.interface
Requires-Dist: zope.lifecycleevent
Requires-Dist: zope.publisher
Requires-Dist: zope.schema (!=6.1,>=3.5.1)
Requires-Dist: zope.security
Requires-Dist: zope.traversing
Requires-Dist: zope.datetime
Provides-Extra: docs
Requires-Dist: Sphinx ; extra == 'docs'
Requires-Dist: sphinx-rtd-theme ; extra == 'docs'
Requires-Dist: repoze.sphinx.autointerface ; extra == 'docs'
Provides-Extra: test
Requires-Dist: zope.configuration ; extra == 'test'
Requires-Dist: zope.schema (>=6.1) ; extra == 'test'
Requires-Dist: zope.testing ; extra == 'test'
Requires-Dist: zope.testrunner ; extra == 'test'
